md_notes_ropc/__init__.py
md_notes_ropc/api_helper.py
md_notes_ropc/configuration.py
md_notes_ropc/decorators.py
md_notes_ropc/md_notes_ropc_client.py
md_notes_ropc/controllers/__init__.py
md_notes_ropc/controllers/base_controller.py
md_notes_ropc/controllers/o_auth_authorization_controller.py
md_notes_ropc/controllers/service_controller.py
md_notes_ropc/controllers/user_controller.py
md_notes_ropc/exceptions/__init__.py
md_notes_ropc/exceptions/api_exception.py
md_notes_ropc/exceptions/o_auth_provider_exception.py
md_notes_ropc/http/__init__.py
md_notes_ropc/http/http_call_back.py
md_notes_ropc/http/http_client.py
md_notes_ropc/http/http_context.py
md_notes_ropc/http/http_method_enum.py
md_notes_ropc/http/http_request.py
md_notes_ropc/http/http_response.py
md_notes_ropc/http/requests_client.py
md_notes_ropc/http/auth/__init__.py
md_notes_ropc/http/auth/o_auth_2.py
md_notes_ropc/models/__init__.py
md_notes_ropc/models/note.py
md_notes_ropc/models/o_auth_provider_error_enum.py
md_notes_ropc/models/o_auth_scope_enum.py
md_notes_ropc/models/o_auth_token.py
md_notes_ropc/models/service_status.py
md_notes_ropc/models/user.py
MdNotes_ROPC-1.0.dist-info/LICENSE
MdNotes_ROPC-1.0.dist-info/METADATA
MdNotes_ROPC-1.0.dist-info/WHEEL
MdNotes_ROPC-1.0.dist-info/top_level.txt
MdNotes_ROPC-1.0.dist-info/RECORD
